[
    {
        "id": "5a799aacf1274bcc815085e2a6181a34",
        "name": {
            "en": "English skills",
            "vi": "Kỹ năng tiếng Anh"
        },
        "channels": [
            {
                "id": "1212d1f0715c4a4ba1f0c55af0028cb8",
                "channel_id": "UCeTVoczn9NOZA9blls3YgUg",
                "title": "Learn English with EnglishClass101.com"
            },
            {
                "id": "ad0f1a210f8949b4bc967f7a99acfbc8",
                "channel_id": "UCvn_XCl_mgQmt3sD753zdJA",
                "title": "Rachel's English"
            },
            {
                "id": "4beeb8646cfe43de84e910ee6dc279f9",
                "channel_id": "UCAQg09FkoobmLquNNoO4ulg",
                "title": "linguamarina"
            },
            {
                "id": "eea94591d6c74e30b077a950258a5f33",
                "channel_id": "UC8pPDhxSn1nee70LRKJ0p3g",
                "title": "English Addict with Mr Duncan"
            },
            {
                "id": "c630f0b455f64100bdcb594b3cf8c578",
                "channel_id": "UCHaHD477h-FeBbVh9Sh7syA",
                "title": "BBC Learning English"
            },
            {
                "id": "12e85e8852e1491f9c7484e19a403bfb",
                "channel_id": "UCKyTokYo0nK2OA-az-sDijA",
                "title": "VOA Learning English"
            },
            {
                "id": "796ccf017ffe410f8e2026cd67007911",
                "channel_id": "UCPeHKeg8RVHOBZWyZijoqow",
                "title": "Học Tiếng Anh Langmaster"
            },
            {
                "id": "83f82e80bcba4bd5a9360840d4ebf11d",
                "channel_id": "UCjsIuhbtDQny5lv4B2b2VOg",
                "title": "Elight Learning English"
            },
            {
                "id": "f932e801465744d59fd15839b74d0949",
                "channel_id": "UCKgpamMlm872zkGDcBJHYDg",
                "title": "Learn English With TV Series"
            },
            {
                "id": "fb27660edd424f84b6c76c3d4302a261",
                "channel_id": "UCnidVRZng96xx-OVc6dK6fQ",
                "title": "IELTS FACE-OFF"
            },
            {
                "id": "980b28455944499cb6d73a8ebe2d5eb5",
                "channel_id": "UCLyr-hfWVCKHcZjV5fg3jbw",
                "title": "English Speeches"
            },
            {
                "id": "170d5a1f1cc54b4da2a3821305c095f1",
                "channel_id": "UCXtMjo8xJqjEhS4A9KUY8GA",
                "title": "Learn English with Jessica"
            },
            {
                "id": "ea78d8b580fb4b60b6328adb4c41ab90",
                "channel_id": "UCxJGMJbjokfnr2-s4_RXPxQ",
                "title": "Speak English With Vanessa"
            },
            {
                "id": "1a42e14551434fbb8fa088a35088a990",
                "channel_id": "UCz4tgANd4yy8Oe0iXCdSWfA",
                "title": "English with Lucy"
            },
            {
                "id": "1fb43a7e735b4e24bf0f09de714bd035",
                "channel_id": "UCNbeSPp8RYKmHUliYBUDizg",
                "title": "Oxford Online English"
            },
            {
                "id": "9ed5691cb0564cdfaed0e7afdd9e3efb",
                "channel_id": "UClvwNCja3aXxqiFrsKC1DPQ",
                "title": "English with Alex · engVid English Classes"
            },
            {
                "id": "8046bff5cb3d424f8b8ed78313892d51",
                "channel_id": "UCJtBaL1PPmTc1ff0nsihR0g",
                "title": "Learn English with Rebecca · engVid"
            },
            {
                "id": "324aa6c1e399424f8a7c529ba2a6764f",
                "channel_id": "UC4cmBAit8i_NJZE8qK8sfpA",
                "title": "English with Ronnie · EnglishLessons4U with engVid"
            },
            {
                "id": "42923f6ada134c0eacb855cba5a77fa8",
                "channel_id": "UCIiFsAO2Gh_vu8OStpjl16A",
                "title": "Business English - Learn with Business English Pod"
            },
            {
                "id": "3b6d01d88e6e46b8985f02a3d1933b29",
                "channel_id": "UCEKXieT70wByfvZwP1CxdPQ",
                "title": "JenniferESL"
            },
            {
                "id": "f8d1cdbbf9e74e23adfec57063b1fa43",
                "channel_id": "UCvgLaFuTGGRXl0eyvBRCifA",
                "title": "Easy English"
            },
            {
                "id": "cde8c989d13e4bb5ba6aff645448f3b1",
                "channel_id": "UCiWN-_fO8NfLsEFUVw6wuHw",
                "title": "Doses Of English"
            },
            {
                "id": "181f1d1ebcc84a47b1f7c585539c573e",
                "channel_id": "UCaRMivfyupj3ucUyJbZbCNg",
                "title": "Anglo-Link"
            },
            {
                "id": "b0fd555a86114c10bdcbc92d7686142f",
                "channel_id": "UCicjynhfFw2LiIQFnoS1JTw",
                "title": "Learn English with Let's Talk - Free English Lessons"
            },
            {
                "id": "7f6d099a9bd64027915b0a0d2e5f2729",
                "channel_id": "UCy-dvmsfmvYXBmt_huqqo1A",
                "title": "English Jade · Learn English with engVid"
            },
            {
                "id": "f31faaa622954da686a03ecdc1b2ec23",
                "channel_id": "UCwA7Aepp7nRUJNa8roQ-6Bw",
                "title": "ENGLISH with James · engVid"
            },
            {
                "id": "b0fa0843510049838febeb696de8fb7e",
                "channel_id": "UCrBhVZa7t7D5tZ979eBqO9g",
                "title": "Benjamin’s English · Learn English with engVid"
            },
            {
                "id": "b29b39efad274cd6868e6ddee19153ea",
                "channel_id": "UCzBGtBze1AIcDmRwD2ZjiAA",
                "title": "Learn English with Gill · engVid"
            },
            {
                "id": "0e47038992c84f1b91895c5468557883",
                "channel_id": "UCVBErcpqaokOf4fI5j73K_w",
                "title": "English with Emma · engVid"
            },
            {
                "id": "1236927a1884490689d1af2fa706ddee",
                "channel_id": "UC8hrVYljKmaDdvGwkes8EQA",
                "title": "Zen English"
            },
            {
                "id": "e164037b08bc464e9bc6a969fb052995",
                "channel_id": "UCu1LmUuVJm4r-UAMkXdHXZA",
                "title": "Easy English Abraão"
            },
            {
                "id": "7069317d9135494b814f56f8e8f0656b",
                "channel_id": "UC9eIq7PwD0WA-2B_Sp7xGdw",
                "title": "English Fluency Journey"
            },
            {
                "id": "ca587ea80ffc45b286cabaf5a8827576",
                "channel_id": "UCQjIS-LqmS0Xz_y2DUUGEZA",
                "title": "Learn English Through Story For Free"
            },
            {
                "id": "fcb8724f3fd1480f85de13cb9277cc17",
                "channel_id": "UCLsI5-B3rIr27hmKqE8hi4w",
                "title": "English Speaking Course"
            },
            {
                "id": "874030ed86b446d590417ce4a1a47d8d",
                "channel_id": "UCoIdrULeenCQ_d1_-ayFuTA",
                "title": "Learn English Through Story"
            },
            {
                "id": "bd3acee773c846428b27a7022f6af6c7",
                "channel_id": "UC_OskgZBoS4dAnVUgJVexcw",
                "title": "Shaw English Online"
            },
            {
                "id": "b9fbf8f555cd4ffa953298ced45ba6ba",
                "channel_id": "UCPqrEgBEHVj4vDITrClNQIw",
                "title": "ABC Learning English"
            },
            {
                "id": "6cc3fbeb6a4143f6be6f9b15c33cec25",
                "channel_id": "UCvzNwI8Qxb_isOnZJb48fiw",
                "title": "Cake English"
            },
            {
                "id": "e4b8b7ef156b42d59932efac63e80e80",
                "channel_id": "UCOtnu-KKoAbN47IuYMeDPOg",
                "title": "British Council | LearnEnglish"
            },
            {
                "id": "aa6df2d869b94943a037b529786dfcfb",
                "channel_id": "UC_0NfufarVw04vDfWFm8z_Q",
                "title": "Adam’s English Lessons · engVid"
            },
            {
                "id": "fd3c55b3cc624e1598efb01959c6c98f",
                "channel_id": "UCiBxcx4_KeR-UtD5qPbcOgg",
                "title": "English for Everyone with Kevin and Liza"
            }
        ]
    },
    {
        "id": "a6ce49a773f545e9b4cee085ccf84785",
        "name": {
            "en": "Travel",
            "vi": "Du lịch"
        },
        "channels": [
            {
                "id": "b42ad5512180435f8c93ac7484a23eda",
                "channel_id": "UCZdQjaSoLjIzFnWsDQOv4ww",
                "title": "Sailing La Vagabonde"
            },
            {
                "id": "21dd7481cbc347fe96e251fe57cd9818",
                "channel_id": "UCvK4bOhULCpmLabd2pDMtnA",
                "title": "Yes Theory"
            },
            {
                "id": "42d814f57c7549478ede79568fb0cc36",
                "channel_id": "UCETOsEEkh5isOVQzRBaOgNQ",
                "title": "Haylsa & Kyle"
            },
            {
                "id": "cd1ab592156d4162a8fb8ef672b194ec",
                "channel_id": "UCt_NLJ4McJlCyYM-dSPRo7Q",
                "title": "Lost LeBlanc"
            },
            {
                "id": "ec90703137034616a25c8aa4cdf19c52",
                "channel_id": "UCy_b-3y4ua9H5GPwIosu0OA",
                "title": "Joyous Travel"
            },
            {
                "id": "9e80cc34fcfb416aa33445e869eabef0",
                "channel_id": "UCh3Rpsdv1fxefE0ZcKBaNcQ",
                "title": "touropia"
            },
            {
                "id": "da80558d9c4a45e7b299794c0e88ca27",
                "channel_id": "UCVrvnobbNGGMsS5n2mJwfOg",
                "title": "FunForLouis"
            },
            {
                "id": "cc2ac8e192cb4b28a5543f93fac350a3",
                "channel_id": "UCAkP51BEzkKimJh7KDflx_g",
                "title": "Ben Brown"
            },
            {
                "id": "176820799b0a4c50896fe25b9c17391c",
                "channel_id": "UCa1WbVCkTqd5ecG6G2adIow",
                "title": "vagabrothers"
            },
            {
                "id": "fc87770fa4a34f7dbc616474754d1011",
                "channel_id": "UCB-Ps5DdRsVAcml-Y43o7RQ",
                "title": "Hey Nadine"
            },
            {
                "id": "d307e4da39e04aca9a567c0ae293e0c4",
                "channel_id": "UCFr3sz2t3bDp6Cux08B93KQ",
                "title": "Wolters World"
            },
            {
                "id": "ae3fc1f7123942b5b1f60a95b84e46ae",
                "channel_id": "UC0Tf8LUUtL3E24Dr28vXkbA",
                "title": "Kristen & Siya"
            },
            {
                "id": "91232b0328464b7093bc5d23f468ad5c",
                "channel_id": "UCfBczdzN3Rf86e7liQYbZRg",
                "title": "PsychoTraveller"
            },
            {
                "id": "ad06b1531d5f4fb1a1776b72bdfb68a9",
                "channel_id": "UCokvlHFyLfpWrgSuZW9uA5Q",
                "title": "GRRRLTRAVELER | Christine Kaaloa"
            },
            {
                "id": "48d4280c252e470483d49aaa465f4a8d",
                "channel_id": "UCVBD2a1uUkhX18B1WVcddzQ",
                "title": "The Planet D"
            },
            {
                "id": "a38db556774a487d98134baa96235c13",
                "channel_id": "UCBo9TLJiZ5HI5CXFsCxOhmA",
                "title": "Gone with the Wynns"
            },
            {
                "id": "5df092db145c4298a661dfb16b7f12bd",
                "channel_id": "UCnTsUMBOA8E-OHJE-UrFOnA",
                "title": "Samuel and Audrey - Travel and Food Videos"
            },
            {
                "id": "ca56896cf52541d29d7d8000fae8bd0d",
                "channel_id": "UCOnj7dA6j1iTFtudrackMag",
                "title": "Eight Miles from Home"
            },
            {
                "id": "1cf29dfc9079424d9ecefe92d5f0fd66",
                "channel_id": "UCkbTTGoBpjX8ogXHCt-aegw",
                "title": "Sorelle Amore"
            },
            {
                "id": "4ba8d52e5b2740f084674c8fcdd2ec63",
                "channel_id": "UCDTINI9skkeZNY2ZXnBqIkQ",
                "title": "Eva zu Beck"
            },
            {
                "id": "e44bc778470d433aae9761b65f148b1e",
                "channel_id": "UCckFCPnDSf9mMCkdEq7tTcQ",
                "title": "The Budgeteers"
            },
            {
                "id": "bbd59cd2542740fca9217b612147c2dd",
                "channel_id": "UC_DmOS_FBvO4H27U7X0OtRg",
                "title": "Fearless & Far"
            },
            {
                "id": "7f7285531eea4149a74287ec89a41eae",
                "channel_id": "UC0Ize0RLIbGdH5x4wI45G-A",
                "title": "Drew Binsky"
            },
            {
                "id": "33c155d313f340faa45661dad87c3002",
                "channel_id": "UCCyR9oAyHGSvZnYoGv3Qu1Q",
                "title": "Japan by Food"
            },
            {
                "id": "51bdecb3e6ea40b38c9864f80a0445cd",
                "channel_id": "UC4ijq8Cg-8zQKx8OH12dUSw",
                "title": "Kara and Nate"
            }
        ]
    },
    {
        "id": "2d6dbd9adc2a47b284c277867be51ac2",
        "name": {
            "en": "Food",
            "vi": "Thức ăn"
        },
        "channels": [
            {
                "id": "a2b24a54911f4f719752c5329a86462d",
                "channel_id": "UCcAd5Np7fO8SeejB1FVKcYw",
                "title": "Best Ever Food Review Show"
            },
            {
                "id": "76c7fea1138d495fb293c00897e00294",
                "channel_id": "UCRIZtPl9nb9RiXc9btSTQNw",
                "title": "Food Wishes"
            },
            {
                "id": "0aafd59c6ce44e01a4e0c3a2541af4f2",
                "channel_id": "UCIEv3lZ_tNXHzL3ox-_uUGQ",
                "title": "Gordon Ramsay"
            },
            {
                "id": "6465f6631e19410e8e0694b3dc025d41",
                "channel_id": "UCjrL1ugI6xGqQ7VEyV6aRAg",
                "title": "BBQ Pit Boys"
            },
            {
                "id": "2a5603c8338849ed9007adb8e2375180",
                "channel_id": "UCl0kP-Cfe-GGic7Ilnk-u_Q",
                "title": "Everyday Food"
            },
            {
                "id": "2b5564d86cf24029b10f1c54318b7956",
                "channel_id": "UCbpMy0Fg74eXXkvxJrtEn3w",
                "title": "Bon Appétit"
            },
            {
                "id": "bdaf42d60aef4ebcbeb530dcf29a274c",
                "channel_id": "UCpSgg_ECBj25s9moCDfSTsA",
                "title": "Jamie Oliver"
            },
            {
                "id": "fd53e6e0cea84cf9b76bb9b0770a7609",
                "channel_id": "UCfyehHM_eo4g5JUyWmms2LA",
                "title": "SORTEDfood"
            },
            {
                "id": "31b2a67fd38842a09e7bedc6fff43b53",
                "channel_id": "UC27C_HWo-UmKkdWGsRJZ8EA",
                "title": "Pailin's Kitchen"
            },
            {
                "id": "8a4dc331ff7f4f7d8ac73c4817ae23a9",
                "channel_id": "UC8gFadPgK2r1ndqLI04Xvvw",
                "title": "Maangchi"
            },
            {
                "id": "b54a3b4b96b340cab2fe27b810fde228",
                "channel_id": "UCMmZEL8jV1B61NKAXcyW87A",
                "title": "Helen's Recipes (Vietnamese Food)"
            },
            {
                "id": "154b583108314c7895a082db90eac7c5",
                "channel_id": "UCCJdqnlqrmTUAYvS6i3nAXA",
                "title": "Angel Wong's Kitchen"
            },
            {
                "id": "20a39963cdb9457e9395c5d24bce65c6",
                "channel_id": "UCNbngWUqL2eqRw12yAwcICg",
                "title": "Laura in the Kitchen"
            },
            {
                "id": "f9f51d5e2d6245cea5d6c0323c845432",
                "channel_id": "UCjwmbv6NE4mOh8Z8VhPUx1Q",
                "title": "Rosanna Pansino"
            },
            {
                "id": "ad7f93203523437f940587ab50ee5021",
                "channel_id": "UCJHA_jMfCvEnv-3kRjTCQXw",
                "title": "Babish Culinary Universe"
            },
            {
                "id": "0b9149650018409c843fb95755d79304",
                "channel_id": "UCYjk_zY-iYR8YNfJmuzd70A",
                "title": "Epic Meal Time"
            },
            {
                "id": "792e04283b7149c1ada3ba70a06993b2",
                "channel_id": "UCyEd6QBSgat5kkC6svyjudA",
                "title": "Mark Wiens"
            },
            {
                "id": "a3e59c3fc9f142e39b89526620a6af2b",
                "channel_id": "UCsP7Bpw36J666Fct5M8u-ZA",
                "title": "How To Cook That"
            },
            {
                "id": "2fe59d26e51b4243a986c340fd98f886",
                "channel_id": "UCiAq_SU0ED1C6vWFMnw8Ekg",
                "title": "The Food Ranger"
            },
            {
                "id": "c8f012cd61b442ca99000186547fc03b",
                "channel_id": "UCvM1hVcRJmVWDtATYarC0KA",
                "title": "How To Cake It"
            },
            {
                "id": "4fa94865fca44e46b21d197879de3719",
                "channel_id": "UCaDY8WjYWy36bnt0RVzSklw",
                "title": "Tipsy Bartender"
            },
            {
                "id": "9f5ca7f91f66434283bbc2497d3fcf8a",
                "channel_id": "UCXOKEdfOFxsHO_-Su3K8SHg",
                "title": "Strictly Dumpling"
            },
            {
                "id": "99b7547af0394b10b4913bcc012f73e3",
                "channel_id": "UCxytOEPP99jj8mqVGAO7haQ",
                "title": "MyCupcakeAddiction"
            },
            {
                "id": "3bf4188e6f764675b785c45609bb190d",
                "channel_id": "UCpprBWvibvmOlI8yJOEAAjA",
                "title": "Cooking with Dog"
            }
        ]
    },
    {
        "id": "2ad7fd6c9c6947afa380d675a71aaf61",
        "name": {
            "en": "Music",
            "vi": "Âm nhạc"
        },
        "channels": [
            {
                "id": "93de1ca94f424e588b622c9777b69f47",
                "channel_id": "UCCTSB5wKKV2NWVUOfeCZCvQ",
                "title": "Fall In Luv"
            },
            {
                "id": "913aa5459be44c93a89697cd2386c215",
                "channel_id": "UC4pcJpUBxP16H1AY1aUy6GA",
                "title": "Cam Lavigne"
            },
            {
                "id": "69c34b8d365d413b943e06d5bd8d78e5",
                "channel_id": "UCjSo8dNDqtwDHX1ahbuA7eQ",
                "title": "S Music"
            },
            {
                "id": "3f3fb69d940942d598a0d066c4c37e37",
                "channel_id": "UCNqFDjYTexJDET3rPDrmJKg",
                "title": "7clouds"
            },
            {
                "id": "846502c2dc054286955d8672cd7ddc02",
                "channel_id": "UCvR2R7j218tzejtTsb_X6Rw",
                "title": "DopeLyrics"
            },
            {
                "id": "3f762ee4afeb4624814a375802628776",
                "channel_id": "UCI0zpW-HyHg745GvGE5kVdw",
                "title": "Deep Chill Mix"
            },
            {
                "id": "ae82b4adca4e4c568c80d318ebbf81fb",
                "channel_id": "UCNvzrZl9MVO76lKviKGAlVA",
                "title": "Acoustic Songs Collection"
            },
            {
                "id": "204b5c85c6074547a60a201e86b9969f",
                "channel_id": "UCG9LCoMgPwWdflKSXkbaiqw",
                "title": "The New Vibe"
            },
            {
                "id": "5d6050feffd04c4c8f9e1c2b27bb8e94",
                "channel_id": "UC0C-w0YjGpqDXGB8IHb662A",
                "title": "Ed Sheeran"
            },
            {
                "id": "da97a059dcd54e87962ce6973064d82b",
                "channel_id": "UCoyGedsMfMU-u_CmV6FSy5g",
                "title": "Myynhh"
            },
            {
                "id": "73b9207e62d4497eb4914a8ed0f03a24",
                "channel_id": "UCEa-JnNdYCIFn3HMhjGEWpQ",
                "title": "John Legend"
            },
            {
                "id": "aaaceb434ef040f6b330de0f601473a0",
                "channel_id": "UCgc00bfF_PvO_2AvqJZHXFg",
                "title": "Boyce Avenue"
            },
            {
                "id": "c2560834c6184c9b8473f5cfc4723d8e",
                "channel_id": "UCrIgjZHLv9la2iR357RuYuA",
                "title": "ConnieTalbotOfficial"
            },
            {
                "id": "a5bd112f4b1d4558822d00994a3d4745",
                "channel_id": "UCtWBCzqucZXq0M8jsqunM0g",
                "title": "Alec Benjamin"
            },
            {
                "id": "b8fd83ead52d42b8b693763ccf3022c3",
                "channel_id": "UC60kwqBXG52dCd-_oUphnwA",
                "title": "JAX"
            },
            {
                "id": "f25181a210c94aebb3f1e2559ddfc7f1",
                "channel_id": "UC3CKhThVWDaprcb3IcnXDfg",
                "title": "Lucy Thomas Music"
            },
            {
                "id": "39760dad0bff47d5ba8f023091b9b5aa",
                "channel_id": "UCb4JB8-ZAeceuR7EPCPOPzg",
                "title": "Andrea Bocelli"
            },
            {
                "id": "464e4c010b8d43e5ad0eb0095b91925e",
                "channel_id": "UCDPM_n1atn2ijUwHd0NNRQw",
                "title": "Coldplay"
            },
            {
                "id": "b32dbd10001e409bbb93870f64fa02f9",
                "channel_id": "UCPNxhDvTcytIdvwXWAm43cA",
                "title": "Selena Gomez"
            },
            {
                "id": "51f02f6aff04440d995cdc4454cd4e43",
                "channel_id": "UCSzok7xBWSxKgNOY_qtzVgQ",
                "title": "Jonah Baker"
            },
            {
                "id": "f5fd019c31ad415ca778385a44c05c1a",
                "channel_id": "UCnzEF-_PurXQTK2uQ-A3Oww",
                "title": "Pink Sweats"
            },
            {
                "id": "cc9b675798dc49958eaf33ab081bf2cc",
                "channel_id": "UC0WP5P-ufpRfjbNrmOWwLBQ",
                "title": "The Weeknd"
            },
            {
                "id": "7d9726002b564429b7717f96026e7b6b",
                "channel_id": "UCwppdrjsBPAZg5_cUwQjfMQ",
                "title": "Charlie Puth"
            },
            {
                "id": "4d4df1fbd55f41298998c39ab71f6f59",
                "channel_id": "UCsRM0YB_dabtEPGPTKo-gcw",
                "title": "Adele"
            },
            {
                "id": "f3fa779a7a354d9e9b3a3a0929cf6038",
                "channel_id": "UCcgqSM4YEo5vVQpqwN-MaNw",
                "title": "Rihanna"
            },
            {
                "id": "505ddcaf316a454dbb175c3d083b4837",
                "channel_id": "UCuHzBCaKmtaLcRAOoazhCPA",
                "title": "Beyoncé"
            },
            {
                "id": "8bc4abb1fd974ded9433f3a77a219c17",
                "channel_id": "UCqECaJ8Gagnn7YCbPEzWH6g",
                "title": "Taylor Swift"
            },
            {
                "id": "9f0b1c16d3504c7eb2309a515bd50b5c",
                "channel_id": "UCByOQJjav0CUDwxCk-jVNRQ",
                "title": "Drake"
            },
            {
                "id": "732356a87f204df2ad4395ff3279b64e",
                "channel_id": "UC9CoOnJkIBMdeijd9qYoT_g",
                "title": "Ariana Grande"
            },
            {
                "id": "37bbabf94acb4e5bac5e4e49344b6e17",
                "channel_id": "UC-8Q-hLdECwQmaWNwXitYDw",
                "title": "KatyPerryVEVO"
            },
            {
                "id": "78a73c0b794d4c549c9b8fe42ae6f690",
                "channel_id": "UCSY5V7BJSrxNvvBF0Drslow",
                "title": "Mark Ronson"
            },
            {
                "id": "eb554f4f269f408d9edbd47fce879816",
                "channel_id": "UCoUM-UJ7rirJYP8CQ0EIaHA",
                "title": "Bruno Mars"
            },
            {
                "id": "f7e2d6632e124d008dd321372cbdcbc8",
                "channel_id": "UCNL1ZadSjHpjm4q9j2sVtOA",
                "title": "Lady Gaga"
            },
            {
                "id": "d592a3ddbc274ced9f32b63076953eeb",
                "channel_id": "UCIwFjwMjI0y7PDBVEO9-bkQ",
                "title": "Justin Bieber"
            },
            {
                "id": "8baf6db54f4843dfa9f014dd75e83caa",
                "channel_id": "UCcYrdFJF7hmPXRNaWdrko4w",
                "title": "Chris Brown"
            },
            {
                "id": "1973a9c9bb90461e8880c6e2a2ed3481",
                "channel_id": "UCeLHszkByNZtPKcaVXOCOQQ",
                "title": "Post Malone"
            },
            {
                "id": "e28fe1bd50f4447cbf26b72604dac723",
                "channel_id": "UCiGm_E4ZwYSHV3bcW1pnSeQ",
                "title": "Billie Eilish"
            }
        ]
    },
    {
        "id": "793620e93e864a93a6cf0378a0d96aba",
        "name": {
            "en": "Kids",
            "vi": "Trẻ em"
        },
        "channels": [
            {
                "id": "852ae92afe2b473cac710fb05d4e79be",
                "channel_id": "UCNHDt6E1ZpHY-YECxEWccUA",
                "title": "Learning Time with Timmy"
            },
            {
                "id": "a354cb12b62044cfa6966782b8adb0e1",
                "channel_id": "UCK5Q72Uyo73uRPk8PmM2A3w",
                "title": "Genevieve's Playhouse - Learning Videos for Kids"
            },
            {
                "id": "5b63f86042884ac7b47925d11044d47b",
                "channel_id": "UC6zhI71atP7YLoZyIyCIGNw",
                "title": "Dave and Ava - Nursery Rhymes and Baby Songs"
            },
            {
                "id": "10bc618da32d492dbc113fc25dc46343",
                "channel_id": "UCx1xhxQyzR4TT6PmXO0khbQ",
                "title": "STEVE AND MAGGIE"
            },
            {
                "id": "43183963a4554a3f86801681f40e6c56",
                "channel_id": "UCbCmjCuTUZos6Inko4u57UQ",
                "title": "Cocomelon - Nursery Rhymes"
            },
            {
                "id": "af5d2449e251439ab5959da50e3a768f",
                "channel_id": "UCLsooMJoIpl_7ux2jvdPB-Q",
                "title": "Super Simple Songs - Kids Songs"
            },
            {
                "id": "f9d27510e87c4db988014616bf340e2c",
                "channel_id": "UCe1VpF4wS_kdcjyTRSXBcnQ",
                "title": "The Singing Walrus - English Songs For Kids"
            },
            {
                "id": "835f5d41e801416c8228f3966ac4cf61",
                "channel_id": "UCBnZ16ahKA2DZ_T5W0FPUXg",
                "title": "ChuChu TV Nursery Rhymes & Kids Songs"
            },
            {
                "id": "638e1111bf064ad69919f1b2e0191afa",
                "channel_id": "UC7Pq3Ko42YpkCB_Q4E981jw",
                "title": "Kids TV - Nursery Rhymes And Baby Songs"
            },
            {
                "id": "88c9afc7ed514e3aa7e1d1e910cfc5b1",
                "channel_id": "UCZzfOkvfLKdKYEWAZ_Vc0zg",
                "title": "Toddler Fun Learning"
            },
            {
                "id": "dfba7a13f2de40049e221536dcd4937a",
                "channel_id": "UC4NALVCmcmL5ntpV0thoH6w",
                "title": "LooLoo Kids - Nursery Rhymes and Children's Songs"
            },
            {
                "id": "c47d4b4e52f64f1fb83696d85099ffbf",
                "channel_id": "UCgbfG5HoczHIkpzxLYH-8Ww",
                "title": "Pokémon Kids TV"
            },
            {
                "id": "c8e033257e494ab0a53dad316ecc7a9d",
                "channel_id": "UCVi_GtP-1stDmhPuWCCQ5KA",
                "title": "Eli Kids - Cartoons & Songs"
            },
            {
                "id": "84ec4573517a4f699c235693e6208a7d",
                "channel_id": "UCNzsYU0aWwjERj-9Y9HUEng",
                "title": "Little Angel: Nursery Rhymes & Kids Songs"
            },
            {
                "id": "0b1f7af4acb940d29c35a696dbcd0c72",
                "channel_id": "UCpzYfBXbEHHQHU2e89jM9Tg",
                "title": "Little Treehouse Nursery Rhymes and Kids Songs"
            },
            {
                "id": "ffa4f38f80a94bb28f5c24173fc40f80",
                "channel_id": "UC56cowXhoqRWHeqfSJkIQaA",
                "title": "Bounce Patrol - Kids Songs"
            },
            {
                "id": "838cbca6314e4818b181bfdad002dfab",
                "channel_id": "UCMsQNXla0kQU5337ipRj1eQ",
                "title": "HeyKids - Nursery Rhymes"
            },
            {
                "id": "6123da9076974ff0a917fb00f59b477a",
                "channel_id": "UCSVtZpbcKdZTNITQtEzY8vA",
                "title": "Baby JoJo Kids Songs"
            },
            {
                "id": "ec30034049cf41489782637f5c0860e1",
                "channel_id": "UC-qWJlvaPME3MWvrY-yjXeA",
                "title": "British Council | LearnEnglish Kids"
            },
            {
                "id": "c4ee5f4921c84c15b99f9f1f87a3d416",
                "channel_id": "UC4P8csyQKa2_0D5-VtITRIg",
                "title": "Fun Kids English"
            },
            {
                "id": "cbedf622a2e6413283a9a1262225639b",
                "channel_id": "UCGwA4GjY4nGMIYvaJiA0EGA",
                "title": "English Singsing"
            },
            {
                "id": "6e3e16979191483fae1c8c26f31fe6ea",
                "channel_id": "UCJzcBX9R38KVkH7sWUn5apA",
                "title": "Super JoJo - Playtime with Friends"
            },
            {
                "id": "cde1edb78abc48dcb00fe23f090aaa52",
                "channel_id": "UCOPzf8kf-FUDs32E7F2wGdg",
                "title": "Fairy Tales and Stories for Kids"
            },
            {
                "id": "12347b4adcef42b0a937b5ce7ab3d71f",
                "channel_id": "UChz5aEi3dfrDVC8-YJsMUDA",
                "title": "T-Series Kids Hut"
            },
            {
                "id": "dcfab407444d494bafab315bb148044c",
                "channel_id": "UC543IxLnWvmFhhNTH50vCaw",
                "title": "BooBoo"
            },
            {
                "id": "2e1dde8012174a9790320501406071bc",
                "channel_id": "UC8mWYDxedkJmUReAiA3ze9w",
                "title": "English Fairy Tales"
            },
            {
                "id": "512e374efeae4b748b6cf8977fee261d",
                "channel_id": "UCpTEsLdeVezbz6XuyHF-nzQ",
                "title": "WOA Fairy Tales - English"
            },
            {
                "id": "da64727c7f1e4931a007a95d61dbfbb7",
                "channel_id": "UCcBXr47HBrCsKplyw6iKf3g",
                "title": "MagicBox English Stories"
            }
        ]
    },
    {
        "id": "4d98707b0ace43a89fc1bd10ce4155b5",
        "name": {
            "en": "Science",
            "vi": "Khoa học"
        },
        "channels": [
            {
                "id": "3233c4dd25324e68be694892a3863ace",
                "channel_id": "UCsXVk37bltHxD1rDPwtNM8Q",
                "title": "Kurzgesagt – In a Nutshell"
            },
            {
                "id": "b22d0dba4ff24e22bab4ad2e56d2a526",
                "channel_id": "UCdsOTr6SmDrxuWE7sJFrkhQ",
                "title": "BBC Earth Lab"
            },
            {
                "id": "fb8aa63d203849e59dd96606de571552",
                "channel_id": "UC7DdEm33SyaTDtWYGO2CwdA",
                "title": "Physics Girl"
            },
            {
                "id": "b15c905399c04cbf932c69f6996d7756",
                "channel_id": "UC6107grRI4m0o2-emgoDnAA",
                "title": "SmarterEveryDay"
            },
            {
                "id": "927c178cea95465eb41681048a3d3701",
                "channel_id": "UCkyfHZ6bY2TjqbJhiH8Y2QQ",
                "title": "thebrainscoop"
            },
            {
                "id": "0648b7dbc9f54cdc8d477d2b29cdfd18",
                "channel_id": "UCt_t6FwNsqr3WWoL6dFqG9w",
                "title": "BrainCraft"
            },
            {
                "id": "88d92c9e70d54fd2a3405e0d984d420d",
                "channel_id": "UCvJiYiBUbw4tmpRSZT2r1Hw",
                "title": "Science Channel"
            },
            {
                "id": "299fc492964c43318a6a01e2e82688be",
                "channel_id": "UCv0aU2eKry3kdSTnFa8QAWA",
                "title": "Science Magazine"
            },
            {
                "id": "d33a7bcb42bd45848574e2eeecfd85cc",
                "channel_id": "UCUHW94eEFW7hkUMVaZz4eDg",
                "title": "minutephysics"
            },
            {
                "id": "58d1ae3ef34348e5b2a59f63ed45ffb6",
                "channel_id": "UCZYTClx2T1of7BRZ86-8fow",
                "title": "SciShow"
            },
            {
                "id": "ead95b97d72e4ed9b82435a6eaa318c7",
                "channel_id": "UCoxcjq-8xIDTYp3uz647V5A",
                "title": "Numberphile"
            },
            {
                "id": "2af68154033147559979183757055408",
                "channel_id": "UCeiYXex_fwgYDonaTcSIk6w",
                "title": "MinuteEarth"
            },
            {
                "id": "67a507869bf74ea68c56260a609827f5",
                "channel_id": "UCB_zuUSmh_PVkqwkaDT-thA",
                "title": "Chemical & Engineering News"
            },
            {
                "id": "864f9f7c62134373841867a5cdbf3540",
                "channel_id": "UCShHFwKyhcDo3g7hr4f1R8A",
                "title": "World Science Festival"
            },
            {
                "id": "21a34a97a0304239928fa5b96ee7a3f0",
                "channel_id": "UCdJ9oJ2GUF8Vmb-G63ldGWg",
                "title": "Reactions"
            },
            {
                "id": "38296a1fdcbe44a5b8203fa60eed9fd3",
                "channel_id": "UCivA7_KLKWo43tFcCkFvydw",
                "title": "Applied Science"
            },
            {
                "id": "16b0445f017445bc844b4715e55fb097",
                "channel_id": "UCTev4RNBiu6lqtx8z1e87fQ",
                "title": "acapellascience"
            },
            {
                "id": "80c5c9842331407083d8dead9fe59b3d",
                "channel_id": "UCLBohbbgb9b138zWn-9maEQ",
                "title": "Interactive Biology"
            },
            {
                "id": "cb0c12c565424f0a9deb0a01c3f6e52f",
                "channel_id": "UCVLZmDKeT-mV4H3ToYXIFYg",
                "title": "Tech Insider"
            },
            {
                "id": "ebf4cf98a8a54af093100fea324e9732",
                "channel_id": "UCH4BNI0-FOK2dMXoFtViWHw",
                "title": "Be Smart"
            }
        ]
    },
    {
        "id": "16fc65a7fa334cc79cf40d4afe357c3a",
        "name": {
            "en": "News",
            "vi": "Tin tức"
        },
        "channels": [
            {
                "id": "6dbdc4d3c3f64304b3e2c53029d8c9d7",
                "channel_id": "UC16niRr50-MSBwiO3YDb3RA",
                "title": "BBC News"
            },
            {
                "id": "5509cd7e67614f91b092d304b4364bd9",
                "channel_id": "UCupvZG-5ko_eiXAupbDfxWw",
                "title": "CNN"
            },
            {
                "id": "ea8caeea7b474e8f9175378418160bbe",
                "channel_id": "UCqnbDFdCpuN8CMEg0VuEBqA",
                "title": "The New York Times"
            },
            {
                "id": "9671c281cdb04bc3a6097742b0a1534c",
                "channel_id": "UC1yBKRuGpC1tSM73A0ZjYjQ",
                "title": "The Young Turks"
            },
            {
                "id": "e94bc3dcd2814f5f8477514fb4419c5a",
                "channel_id": "UCbWUEnTRHb3bRdrnovq8iuA",
                "title": "Football Daily"
            },
            {
                "id": "33b680cf118f498292bc7714bc43a1b9",
                "channel_id": "UCNAf1k0yIjyGu3k9BwAg3lg",
                "title": "Sky Sports Football"
            },
            {
                "id": "c601a1e92b4b4fc0bad6d75bc91647b9",
                "channel_id": "UCw3fku0sH3qA3c3pZeJwdAw",
                "title": "Daily Mail"
            },
            {
                "id": "55af9280ff4a404b9643f694a2dc7efe",
                "channel_id": "UCtESv1e7ntJaLJYKIO1FoYw",
                "title": "Periodic Videos"
            },
            {
                "id": "d146574821ff47f190cce5cba1985e54",
                "channel_id": "UCBi2mrWuNuyYy4gbM6fU18Q",
                "title": "ABC News"
            },
            {
                "id": "9b521c10daab4ee680aa72565e4ce62d",
                "channel_id": "UC8p1vwvWtl6T73JiExfWs1g",
                "title": "CBS News"
            },
            {
                "id": "bda6a16ce15941d288bc2ea853cd4ed6",
                "channel_id": "UCXIJgqnII2ZOINSWNOGFThA",
                "title": "Fox News"
            },
            {
                "id": "59fe15cb98b2410d93390902cf85e959",
                "channel_id": "UCeY0bbntWzzVIaj2z3QigXg",
                "title": "NBC News"
            },
            {
                "id": "8770893971324609914b906fd4048f2e",
                "channel_id": "UC0hy7TcR1gGD8nQBqrF2FaA",
                "title": "ACC Digital Network"
            },
            {
                "id": "24e13e631cee47d4992b3bef130c4c93",
                "channel_id": "UCvJJ_dzjViJCoLf5uKUTwoA",
                "title": "CNBC"
            }
        ]
    },
    {
        "id": "0bb74883f7aa48168a4a7e50010cb978",
        "name": {
            "en": "Tech",
            "vi": "Công nghệ"
        },
        "channels": [
            {
                "id": "16471372fe4e46e5bf6d61bb102059c9",
                "channel_id": "UCsTcErHg8oDvUnTzoqsYeNw",
                "title": "Unbox Therapy"
            },
            {
                "id": "208ee0bddff745d5ad581a8043801d8e",
                "channel_id": "UCBJycsmduvYEL83R_U4JriQ",
                "title": "Marques Brownlee"
            },
            {
                "id": "854c837311f5407ea4895785ba44857c",
                "channel_id": "UCXuqSBlHAE6Xw-yeJA0Tunw",
                "title": "Linus Tech Tips"
            },
            {
                "id": "87d0cb0d8c9f46778629797586550e2b",
                "channel_id": "UCMiJRAwDNSNzuYeN2uWa0pA",
                "title": "Mrwhosetheboss"
            },
            {
                "id": "8ae81672afe94eeda11626634d9da859",
                "channel_id": "UCXGgrKt94gR6lmN4aN3mYTg",
                "title": "Austin Evans"
            },
            {
                "id": "d5ab5c80be184891ba6e7ed0306c2f64",
                "channel_id": "UCgyqtNWZmIxTx3b6OxTSALw",
                "title": "Android Authority"
            },
            {
                "id": "5e141cf4beae4d4fb0798625effe0105",
                "channel_id": "UCddiUEpeqJcYeBxX1IVBKvQ",
                "title": "The Verge"
            },
            {
                "id": "ac207279facb4077994beddf61111b69",
                "channel_id": "UCOmcA3f_RrH6b9NmcNa4tdg",
                "title": "CNET"
            },
            {
                "id": "2f5f18a38bb34196862315ff57fc9b26",
                "channel_id": "UC9fSZHEh6XsRpX-xJc6lT3A",
                "title": "UrAvgConsumer"
            },
            {
                "id": "b7cf0aaf59e040fda6c58af748e03beb",
                "channel_id": "UCtXKDgv1AVoG88PLl8nGXmw",
                "title": "Google TechTalks"
            },
            {
                "id": "a8677d116f9a4b18abe963279d2138b1",
                "channel_id": "UCptwuAv0XQHo1OQUSaO6NHw",
                "title": "Max Tech"
            },
            {
                "id": "5a459ad26bf446d486a7886f25a33adf",
                "channel_id": "UCIgQksZ_4IvQ_VAqBWW81bg",
                "title": "Max Yuryev"
            },
            {
                "id": "cfd6ff3290214daa93176b86435a443d",
                "channel_id": "UC0vBXGSyV14uvJ4hECDOl0Q",
                "title": "Techquickie"
            },
            {
                "id": "14eb0445c20447a399c0d60bb1a12bcb",
                "channel_id": "UCey_c7U86mJGz1VJWH5CYPA",
                "title": "iJustine"
            },
            {
                "id": "74d47bbf87f24273b4eb0d6560a7a248",
                "channel_id": "UCUq3Rn72jfQ-86CaCxj7XzA",
                "title": "Created Tech"
            },
            {
                "id": "3feacf0b5b10415f88c7f9cc840beca5",
                "channel_id": "UC09qASY4ixFS-KXIH6Nw0rg",
                "title": "Gerald Undone"
            },
            {
                "id": "a21cb46ef1c54516b003b6b3b2e284a0",
                "channel_id": "UC9uPmpbVinTDL4-aZN-Y1Uw",
                "title": "JesseDriftwood"
            },
            {
                "id": "cbfdc18a07c24131ba226efc7d2d65e2",
                "channel_id": "UC3DkFux8Iv-aYnTRWzwaiBA",
                "title": "Peter McKinnon"
            },
            {
                "id": "13fcedfc12524241afad8aaaf8e26ce0",
                "channel_id": "UCDlQwv99CovKafGvxyaiNDA",
                "title": "Jonathan Morrison"
            },
            {
                "id": "fef2c8ffcfb643aabbeb8eff74742239",
                "channel_id": "UChtY6O8Ahw2cz05PS2GhUbg",
                "title": "Make:"
            },
            {
                "id": "45795986784c4342b45211e196cf922c",
                "channel_id": "UCYO_jab_esuFRV4b17AJtAw",
                "title": "3Blue1Brown"
            },
            {
                "id": "7714d1442339482eb3ba72d0e611e11e",
                "channel_id": "UC29ju8bIPH5as8OGnQzwJyA",
                "title": "Traversy Media"
            },
            {
                "id": "5c1570ca8bc74eab86c5705af8cd8271",
                "channel_id": "UC8ENHE5xdFSwx71u3fDH5Xw",
                "title": "ThePrimeagen"
            },
            {
                "id": "4265b56c5b594fd5961f56793b455a5b",
                "channel_id": "UCRPMAqdtSgd0Ipeef7iFsKw",
                "title": "Gaurav Sen"
            },
            {
                "id": "4425c3cbae1641178e4e739298891806",
                "channel_id": "UC-8QAzbLcRglXeN_MY9blyw",
                "title": "Ben Awad"
            },
            {
                "id": "1a1f2747aaf94befb0d9f9a2eb825dbf",
                "channel_id": "UCFe6jenM1Bc54qtBsIJGRZQ",
                "title": "patrickJMT"
            },
            {
                "id": "089807b1219248fdbeb65336ef30a6ea",
                "channel_id": "UClb90NQQcskPUGDIXsQEz5Q",
                "title": "Dev Ed"
            },
            {
                "id": "1b3a6d8ca3eb48c19ee888549a0050eb",
                "channel_id": "UCW5YeuERMmlnqo4oq8vwUpg",
                "title": "The Net Ninja"
            }
        ]
    },
    {
        "id": "b2bc9ac0c46044b08c2efe8ad1f214ca",
        "name": {
            "en": "Beauty",
            "vi": "Làm đẹp"
        },
        "channels": [
            {
                "id": "9d5a29bca78341ef81ae4e4444fcbff9",
                "channel_id": "UCBNs31xysxpAGMheg8OrngA",
                "title": "Yuya"
            },
            {
                "id": "0b28172fbeef434ca56c11146f250896",
                "channel_id": "UCB0d0JLn1WcGYcwwZ87d2LA",
                "title": "Rclbeauty101"
            },
            {
                "id": "b2d085759b40458998c74cd74bb57da4",
                "channel_id": "UCkvK_5omS-42Ovgah8KRKtg",
                "title": "jeffreestar"
            },
            {
                "id": "19fd2b683e064cfda0f4fc5fbbcc99f2",
                "channel_id": "UCzTKskwIc_-a0cGvCXA848Q",
                "title": "NikkieTutorials"
            },
            {
                "id": "fcf5a27add9940bd83b0f74b0b032812",
                "channel_id": "UCRSvEADlY-caz3sfDNwvR1A",
                "title": "Huda Beauty"
            },
            {
                "id": "5c9f9b75158a46e1a19f57633ad10404",
                "channel_id": "UCrUbqTCagwsaP2Fmr0p1TsA",
                "title": "Zoe Sugg"
            },
            {
                "id": "3677b7d8ba5c48fa97fbea059976b9fa",
                "channel_id": "UCbAwSkqJ1W_Eg7wr3cp5BUA",
                "title": "Safiya Nygaard"
            },
            {
                "id": "80aa2c8343f94da093728ae63483bea6",
                "channel_id": "UCucot-Zp428OwkyRm2I7v2Q",
                "title": "James Charles"
            },
            {
                "id": "7116ed70dafb48a1a7d334c9dc9e6a6c",
                "channel_id": "UC0YvTCy1I4_a-3pn47_5DBA",
                "title": "SaraBeautyCorner - DIY, Comedy, Makeup, Nail Art"
            },
            {
                "id": "070ab39b7fed465d8115b66c4eb05019",
                "channel_id": "UCbO9bltbkYwa56nZFQx6XJg",
                "title": "Manny Mua"
            },
            {
                "id": "19b6ce8211d54cd0b291777265e9e974",
                "channel_id": "UC_GvMVffgctSISDkeWlKhXQ",
                "title": "dope2111"
            },
            {
                "id": "51a9e7530495414dbb9de8630eb63ab2",
                "channel_id": "UCLFW3EKD2My9swWH4eTLaYw",
                "title": "Chloe Morello"
            },
            {
                "id": "0ca0f1c56f884b06ab17cb80e664961a",
                "channel_id": "UCCvoAe__WFYMNAEN-C-CtYA",
                "title": "Wayne Goss"
            },
            {
                "id": "30eb4c1c174a4854b4988343850d37b4",
                "channel_id": "UCG9nVSLp4nQlW79sY5ihRrg",
                "title": "Desi Perkins"
            },
            {
                "id": "ae60f73ca14842449de95af253467104",
                "channel_id": "UCz5ppm1BYc7tgUYIel3EWJw",
                "title": "Weylie Hoang"
            },
            {
                "id": "5555c782e8184463bdb9e1fcb7e9941e",
                "channel_id": "UCc6W7efUSkd9YYoxOnctlFg",
                "title": "Bethany Mota"
            },
            {
                "id": "154d531bcb874c88a15a72261e25cc5c",
                "channel_id": "UC21yq4sq8uxTcfgIxxyE9VQ",
                "title": "Carli Bybel"
            },
            {
                "id": "725612279d5c446db0a1a42f47a45f4b",
                "channel_id": "UCXTAdFsBmxNK3_c8MUvSviQ",
                "title": "Christen Dominique"
            },
            {
                "id": "e8cc14fc206f48e0ae42b2f7a0ec2e94",
                "channel_id": "UCzJIliq68IHSn-Kwgjeg2AQ",
                "title": "Jackie Aina"
            },
            {
                "id": "ecec209314754d4ea35d8b4f062859f7",
                "channel_id": "UCDl9AK32Xzr_2UOxjt03f6w",
                "title": "Camila Coelho"
            },
            {
                "id": "ea36d8ad68654d2d9e105e164c30e6ec",
                "channel_id": "UCMpOz2KEfkSdd5JeIJh_fxw",
                "title": "Shaaanxo"
            },
            {
                "id": "cbd3f84a2a754874ae827b8a6d99b1e6",
                "channel_id": "UCXbQzhqSvgVZTUyi1T4AU3w",
                "title": "Lauren Curtis"
            },
            {
                "id": "c7560a9962144175b8d1ec03651d818f",
                "channel_id": "UCroDJPcFCf6DBmHns6Xeb8g",
                "title": "Nyma Tang"
            },
            {
                "id": "862e7d61a09d4710b4cfd9140b621a66",
                "channel_id": "UC8v4vz_n2rys6Yxpj8LuOBA",
                "title": "KathleenLights"
            },
            {
                "id": "c6be0cb460c744feb23117b25aebe805",
                "channel_id": "UCgWfS_47YPVbKx5EK4FLm4A",
                "title": "Jenn Im"
            }
        ]
    },
    {
        "id": "7752ef4cdf3e4b1bb71847a3e763aaeb",
        "name": {
            "en": "Comedy",
            "vi": "Hài"
        },
        "channels": [
            {
                "id": "ce1a617d6ffd4bb584b4843a6666df4b",
                "channel_id": "UCp0hYYBW6IMayGgR-WeoCvQ",
                "title": "TheEllenShow"
            },
            {
                "id": "8a230c7d4ba44f4ab8ff248f8928beab",
                "channel_id": "UCY30JRSgfhYXA6i6xX1erWg",
                "title": "Smosh"
            },
            {
                "id": "2945ba202c65466fa513e2463c58dba1",
                "channel_id": "UCJ0uqCI0Vqr2Rrt1HseGirg",
                "title": "The Late Late Show with James Corden"
            },
            {
                "id": "887c108b87d941c99870bff15b665c75",
                "channel_id": "UCV9_KinVpV-snHe3C3n1hvA",
                "title": "shane"
            },
            {
                "id": "540703f3930444fbb5211fe830924032",
                "channel_id": "UC9gFih9rw0zNCK3ZtoKQQyA",
                "title": "JennaMarbles"
            },
            {
                "id": "e1826bc8d47140e3bfbb6e3bc5d87c54",
                "channel_id": "UC8-Th83bH_thdKZDJCrn88g",
                "title": "The Tonight Show Starring Jimmy Fallon"
            },
            {
                "id": "5a9a88abda2f4c4d8fa7371983d1ce72",
                "channel_id": "UCxSz6JVYmzVhtkraHWZC7HQ",
                "title": "Liza Koshy"
            },
            {
                "id": "64213960aa4340a99a85ed7c4e8455da",
                "channel_id": "UCfm4y4rHF5HGrSr-qbvOwOg",
                "title": "Lilly Singh"
            },
            {
                "id": "94937f2c8e544c24b26ecbc14352dcce",
                "channel_id": "UCPDis9pjXuqyI7RYLJ-TTSA",
                "title": "FailArmy"
            }
        ]
    },
    {
        "id": "e57227c9d78b48bca2807c3d38ef13bc",
        "name": {
            "en": "Animation",
            "vi": "Hoạt hình"
        },
        "channels": [
            {
                "id": "d3aac3419c244cd0af90a6a69f7180ad",
                "channel_id": "UCo8bcnLyZH8tBIH9V1mLgqQ",
                "title": "TheOdd1sOut"
            },
            {
                "id": "08d7a0ff840e466dabebe65a9ca24485",
                "channel_id": "UCWXCrItCF6ZgXrdozUS-Idw",
                "title": "ExplosmEntertainment"
            },
            {
                "id": "94b94f158ba44d8b9a995e9b1f3f51da",
                "channel_id": "UCHCph-_jLba_9atyCZJPLQQ",
                "title": "How It Should Have Ended"
            },
            {
                "id": "1cbe62c5de564629932106ecc8fc96b9",
                "channel_id": "UCY6Ij8zOds0WJEeqCLOnqOQ",
                "title": "Alex Meyers"
            },
            {
                "id": "d6d60061d6b54eeaa311027f0c475d44",
                "channel_id": "UC0gEw6pgNkLkkzMwzX4UtHA",
                "title": "Egoraptor"
            },
            {
                "id": "eae52148ed654176a49787fd827dde5b",
                "channel_id": "UCV5wuGZmg_FGQp25uzKKDaw",
                "title": "OneyNG"
            },
            {
                "id": "74349aec3eed45efa2028fbd9f5f6a9c",
                "channel_id": "UCmvXfmJEtURCEtHNbMXfDqg",
                "title": "hotdiggedydemon"
            },
            {
                "id": "f999e36295944601a891a2f30224260c",
                "channel_id": "UC1D26ByrbZVwuMgjVWmsOuw",
                "title": "Frame Order"
            },
            {
                "id": "33b19b6bed5f4d47a7bac173f7ebcbc5",
                "channel_id": "UCn1XB-jvmd9fXMzhiA6IR0w",
                "title": "Domics"
            },
            {
                "id": "4dcdf495fbe34c1da6d70ad6606b744a",
                "channel_id": "UCUKi4zY5ETSqrKAjTBgjM-g",
                "title": "sWooZie"
            },
            {
                "id": "50d6780bcd9d45a7bce57625ae38ef6e",
                "channel_id": "UCGwu0nbY2wSkW8N-cghnLpA",
                "title": "Jaiden Animations"
            },
            {
                "id": "5ef898612a2042a28010b4b83bbb1622",
                "channel_id": "UCIA9jUDnKVMYc4SmqTxcwqg",
                "title": "Cartoon Hangover"
            },
            {
                "id": "9e7ea7b0da984963b24590f6b19c0bd7",
                "channel_id": "UC-1rx8j9Ggp8mp4uD0ZdEIA",
                "title": "TheCGBros"
            },
            {
                "id": "8f1bac0704ab4ff4a907712cbb746cc9",
                "channel_id": "UCir4goG7LBQCh5rc3frkHuA",
                "title": "Harry Partridge"
            },
            {
                "id": "fbac77e220c447b985bfa2e0c61038cf",
                "channel_id": "UCV6g95OBbVtFmN9uiJzkFqQ",
                "title": "CircleToonsHD"
            },
            {
                "id": "a3211857f7304a078c668f96ad73d5fc",
                "channel_id": "UCSS6UvWXW8OZD9wpIVkD0YA",
                "title": "Eddsworld"
            },
            {
                "id": "860ad315df2e4258a3cdb111d01e80a7",
                "channel_id": "UCvUmwreRrbxeR1mbmojj8fg",
                "title": "SomeThingElseYT"
            },
            {
                "id": "29961258256c4880b87fd19a1a72bcd1",
                "channel_id": "UCsDmESjqNPukDmVnuneLrqw",
                "title": "Alex Clark"
            },
            {
                "id": "d9bd19bbe36d4092b942cec5a90beded",
                "channel_id": "UCgNg3vwj3xt7QOrcIDaHdFg",
                "title": "PolyMatter"
            }
        ]
    },
    {
        "id": "afc67b670f0f4f28984a92ac1911ff4d",
        "name": {
            "en": "History",
            "vi": "Lịch sử"
        },
        "channels": [
            {
                "id": "0d54c6b95bcf48e78c2175af83e2b868",
                "channel_id": "UC9MAhZQQd9egwWCxrwSIsJQ",
                "title": "HISTORY"
            },
            {
                "id": "e13016ac4dfb40d397ef13e48bbf697d",
                "channel_id": "UClfEht64_NrzHf8Y0slKEjw",
                "title": "AlternateHistoryHub"
            },
            {
                "id": "877425f0cc7a41f399f7e80f8fd42548",
                "channel_id": "UC510QYlOlKNyhy_zdQxnGYw",
                "title": "Simple History"
            },
            {
                "id": "a1516e33c8f643d7a32c6fa3336c018c",
                "channel_id": "UCNIuvl7V8zACPpTmmNIqP2A",
                "title": "OverSimplified"
            },
            {
                "id": "28350b80dccb4a8c9aa24de66ef25915",
                "channel_id": "UCggHoXaj8BQHIiPmOxezeWA",
                "title": "History Buffs"
            },
            {
                "id": "50ce27209d2944e18a7bd1f169c4e214",
                "channel_id": "UC88lvyJe7aHZmcvzvubDFRg",
                "title": "Timeline - World History Documentaries"
            },
            {
                "id": "44604f3400494c32bf4250587a5c1b17",
                "channel_id": "UCodbH5mUeF-m_BsNueRDjcw",
                "title": "Overly Sarcastic Productions"
            },
            {
                "id": "127c20a386374ccfa285eb1465d7798a",
                "channel_id": "UCv_vLHiWVBh_FR9vbeuiY-A",
                "title": "Historia Civilis"
            },
            {
                "id": "2734730f94874fd0a690110ba472c90f",
                "channel_id": "UCx-dJoP9hFCBloY9qodykvw",
                "title": "BazBattles"
            },
            {
                "id": "87fe697056904974af2db665e99e0d87",
                "channel_id": "UCHdluULl5c7bilx1x1TGzJQ",
                "title": "Feature History"
            }
        ]
    },
    {
        "id": "52246e2f999048aa9bdc7dbb2d3290bb",
        "name": {
            "en": "Yoga",
            "vi": "Yoga"
        },
        "channels": [
            {
                "id": "015c838a3f7842d3867dbb236752cb3f",
                "channel_id": "UCFKE7WVJfvaHW5q283SxchA",
                "title": "Yoga With Adriene"
            },
            {
                "id": "a42a83e113ed4023a4fb3995c27f0da3",
                "channel_id": "UCGb34D3ThpmjLNn-FLv2_yQ",
                "title": "PsycheTruth"
            },
            {
                "id": "aaf6de125e3f475bab512e0761e50642",
                "channel_id": "UCxYVPua6HC46HzgT8IIn3vg",
                "title": "Yoga With Bird"
            },
            {
                "id": "b0e9c224fce349fdb7815c0844623551",
                "channel_id": "UCI9s9nFu2m3K2CvhO2QVfTg",
                "title": "Candace Cabrera"
            },
            {
                "id": "4723c3edf9d0413e8e1c7317cc1f62d3",
                "channel_id": "UCciuZl2ydLCvN5txlLW0rIg",
                "title": "Yoga With Tim"
            },
            {
                "id": "1468c8aad9054d3c86f33112b6d4c32c",
                "channel_id": "UCWN2FPlvg9r-LnUyepH9IaQ",
                "title": "Boho Beautiful Yoga"
            },
            {
                "id": "480acf2e442741328016333a6709fb8a",
                "channel_id": "UCX32D3gKXENrhOXdZjWWtMA",
                "title": "Yoga with Kassandra"
            },
            {
                "id": "dc2090b5ab67432cae84253774163474",
                "channel_id": "UCpQ34afVgk8cRQBjSJ1xuJQ",
                "title": "MadFit"
            },
            {
                "id": "7b53b0a55dde41618a496afc948b73e1",
                "channel_id": "UCIXZNvQNioXFkc_Z-dfprrw",
                "title": "Jessica Richburg"
            }
        ]
    },
    {
        "id": "2e15b63f381e4440869323c408a6f84e",
        "name": {
            "en": "Education",
            "vi": "Giáo dục"
        },
        "channels": [
            {
                "id": "e3074281f4594c3f9029dbd37fa868ee",
                "channel_id": "UCAuUUnT6oDeKwE6v1NGQxug",
                "title": "TED"
            },
            {
                "id": "45d0737169d740249ea0dca501eda202",
                "channel_id": "UCsT0YIqwnpJCM-mx7-gSA4Q",
                "title": "TEDx Talks"
            },
            {
                "id": "71f28977dfce4780b03319b2e3750115",
                "channel_id": "UCsooa4yRKGN_zEE8iknghZA",
                "title": "TED-Ed"
            },
            {
                "id": "2ee6d3b5187e4b079307a0237dfb3502",
                "channel_id": "UCX6b17PVsYBQ0ip5gyeme-Q",
                "title": "CrashCourse"
            },
            {
                "id": "e41badc9020542738542df0768a4425b",
                "channel_id": "UC2C_jShtL725hvbm1arSV9w",
                "title": "CGP Grey"
            },
            {
                "id": "6a199fa805cf4d4cb8e34dbc5728d137",
                "channel_id": "UC6nSFpj9HTCZ5t-N3Rm3-HA",
                "title": "Vsauce"
            },
            {
                "id": "7170b351415041e286cc323c5ca7024b",
                "channel_id": "UC4a-Gbdw7vOaccHmFo40b9g",
                "title": "Khan Academy"
            },
            {
                "id": "b615a5104f0749258d5656788494acd8",
                "channel_id": "UCHnyfMqiRRG1u-2MsSQLbXA",
                "title": "Veritasium"
            },
            {
                "id": "faeb0ed2a2d14aad9d1fb1aacd850934",
                "channel_id": "UCC552Sd-3nyi_tk2BudLUzA",
                "title": "AsapSCIENCE"
            },
            {
                "id": "d0ebc7f2241448879127c99a777e53ee",
                "channel_id": "UCvQECJukTDE2i6aCoMnS-Vg",
                "title": "Big Think"
            }
        ]
    },
    {
        "id": "665cfa0df0814368b80b4b465af6f0d2",
        "name": {
            "en": "Fitness",
            "vi": "Thể chất"
        },
        "channels": [
            {
                "id": "ea138bcb2e8f47bb90015e3fc774cc4a",
                "channel_id": "UCEr4irFkzHnhPt0uG8lOpug",
                "title": "Nick's Strength and Power"
            },
            {
                "id": "3b8dc033b4694f1a8ea6a8079df9c1ff",
                "channel_id": "UCXxIurzUx2ztE6D5IzcyTcw",
                "title": "Love Sweat Fitness"
            },
            {
                "id": "db6c25444c3a4a60abc32bbea457e941",
                "channel_id": "UCXIJ2-RSIGn53HA-x9RDevA",
                "title": "HASfit"
            },
            {
                "id": "68f71357c11a49aaa45b15639329a64f",
                "channel_id": "UCnP_T4dI2JYG7BnH42PC9qw",
                "title": "Joanna Soh Official"
            },
            {
                "id": "a3ab599249ba4c15a9a594068290da70",
                "channel_id": "UCjzSBCC2yv7dZmD5dQxV2ug",
                "title": "OfficialBarstarzz"
            },
            {
                "id": "3406179b352d410686324644029ebd24",
                "channel_id": "UCA9k6Z3B9ywXmwKh-zpBwfw",
                "title": "BodyFit By Amy"
            },
            {
                "id": "531a82ca93b3475aaaf80b64e64c30f5",
                "channel_id": "UCM1Nde-9eorUhq-teaWlgUA",
                "title": "XHIT Daily"
            },
            {
                "id": "e65bdd95ec2f4e498ab7ce22ac21ddc3",
                "channel_id": "UCyqR7WkL8i1b6xtSssDmW9w",
                "title": "The Fitness Marshall"
            },
            {
                "id": "61b0fb6906ae44a69ccc9d7a32a52f7d",
                "channel_id": "UCeqR0F3O1V11CiiOaJbd1pw",
                "title": "MattDoesFitness"
            },
            {
                "id": "25e5d2caa5cf41eaa30cd5c263250179",
                "channel_id": "UCs_DvR0g9o7wDgmY3fzbhMw",
                "title": "TheLeanMachines"
            },
            {
                "id": "aa95dc9a5aeb4f3380a8a9260a9e7d52",
                "channel_id": "UCg_tz2iw7_-gf2xIL-DdM2g",
                "title": "Kali Muscle"
            },
            {
                "id": "4fdd282fab13475f95aa1c7f704f2d00",
                "channel_id": "UCn5TkjQimltAs0PLfSm3mEA",
                "title": "Molly Bailey"
            },
            {
                "id": "fbfee0ee59624ea6a1a30a24b1c10f7f",
                "channel_id": "UCEtMRF1ywKMc4sf3EXYyDzw",
                "title": "ScottHermanFitness"
            },
            {
                "id": "8d8d079966d34742bf97872e80745c6b",
                "channel_id": "UCjfG0dyMUiqKleUnkX6zBrA",
                "title": "Natacha Océane"
            },
            {
                "id": "d98976b1724a48f99155ad6f503e869c",
                "channel_id": "UCBINFWq52ShSgUFEoynfSwg",
                "title": "POPSUGAR Fitness"
            },
            {
                "id": "3454ec5d7ce147adaf790f9bb8ef803c",
                "channel_id": "UCgBTevPW8fsH4pQNrLufOsQ",
                "title": "Tone It Up"
            },
            {
                "id": "6b6b9dc2c9c24827b9dc9464cac2a636",
                "channel_id": "UCAxW1XT0iEJo0TYlRfn6rYQ",
                "title": "The Body Coach TV"
            },
            {
                "id": "58029e17d39146339b29d6d52392f6f7",
                "channel_id": "UCa9_TpiSkqYwcr35uh5N7Og",
                "title": "NateBowerFitness"
            },
            {
                "id": "c2c4722652bb422ba75e98cb02db1c27",
                "channel_id": "UCiP6wD_tYlYLYh3agzbByWQ",
                "title": "FitnessBlender"
            }
        ]
    },
    {
        "id": "83d8f94d866349649f3de53042762144",
        "name": {
            "en": "Medical",
            "vi": "Y khoa"
        },
        "channels": [
            {
                "id": "a3d1aa2de43b405ba613c1f7cd4f7161",
                "channel_id": "UCesNt4_Z-Pm41RzpAClfVcg",
                "title": "Armando Hasudungan"
            },
            {
                "id": "5806607ca23c4a0ea102622642e627a0",
                "channel_id": "UCK0oFgaI_-VTHBrRBUjtVGQ",
                "title": "One Minute Medical School"
            },
            {
                "id": "ea27465768554ee6a2ffbde2053ec3a9",
                "channel_id": "UCjG-bUhM813LndEDNOJNCcw",
                "title": "Harvard Medical School"
            },
            {
                "id": "6440dde2405e48ca91a1ac476ffda168",
                "channel_id": "UC0l4yG9XqYtrR4E9lpzk7Ow",
                "title": "The National Library of Medicine"
            },
            {
                "id": "50bdc984cd4f44f08715885e4f8d4027",
                "channel_id": "UCG-iSMVtWbbwDDXgXXypARQ",
                "title": "MedCram - Medical Lectures Explained CLEARLY"
            },
            {
                "id": "d6016a08a7a14f18ad6099cf7634307e",
                "channel_id": "UCqf69ZzuEHEodRqn7C88K5w",
                "title": "iMedicalSchool"
            },
            {
                "id": "73066686722341a0b442417bc898e99c",
                "channel_id": "UCOHfqHMhHvfQCYJDXfpSAiw",
                "title": "nabil ebraheim"
            },
            {
                "id": "30d793d426574ca997b0d65b0a8d654d",
                "channel_id": "UCJayvjGvKEblkA3KYK1BQQw",
                "title": "khanacademymedicine"
            },
            {
                "id": "cdad6e8329764e9e93f2f8e60db98f5e",
                "channel_id": "UCPHpx55tgrbm8FrYYCflAHw",
                "title": "Dr. Najeeb Lectures"
            },
            {
                "id": "4f76fdfccea44347bb6c6dc88b43f409",
                "channel_id": "UCFq5vPnNRNNNysLrktz4aSw",
                "title": "Strong Medicine"
            },
            {
                "id": "9c8a4fe6919346969f4e0fe2238712b7",
                "channel_id": "UCbYmF43dpGHz8gi2ugiXr0Q",
                "title": "Lecturio Medical"
            },
            {
                "id": "9000ee18d4e24062884331a287f1085d",
                "channel_id": "UCFPvnkCZbHfBvV8ApBBE0vA",
                "title": "JJ Medicine"
            },
            {
                "id": "3d4f6e1e3afa46968f63225e6e8b817c",
                "channel_id": "UCabaQPYxxKepWUsEVQMT4Kw",
                "title": "Healthcare Triage"
            },
            {
                "id": "2ab92f16254d40c5a9b55ebe114c2293",
                "channel_id": "UCxmmyyWrLMpbQidP1d7943w",
                "title": "American Cancer Society"
            },
            {
                "id": "46c6547a713d4643b17fe7d00462474d",
                "channel_id": "UCaEEm-0s0x3MHg9jzFcHuQQ",
                "title": "Siemens"
            },
            {
                "id": "d52c02f6a924408fbc2082a21337ade6",
                "channel_id": "UCiMg06DjcUk5FRiM3g5sqoQ",
                "title": "Centers for Disease Control and Prevention (CDC)"
            },
            {
                "id": "253a0c02f1ca405b9f6dac7ca3055c7a",
                "channel_id": "UCBFsmJJch-ZigYRmqGrx56A",
                "title": "Philips Healthcare"
            }
        ]
    },
    {
        "id": "2a70206827fd4bcf96f80ef9e8ce4aee",
        "name": {
            "en": "Gaming",
            "vi": "Trò chơi"
        },
        "channels": [
            {
                "id": "d42498be7828452e9151db2f8c0819e1",
                "channel_id": "UCKqH_9mk1waLgBiL2vT5b9g",
                "title": "VanossGaming"
            },
            {
                "id": "5ec6a7ae513141049f07c620109bd251",
                "channel_id": "UC7_YxT-KID8kRbqZo7MyscQ",
                "title": "Markiplier"
            },
            {
                "id": "7d33cec534674ec0a2ccaa1eb5ccc0b6",
                "channel_id": "UCYzPXprvl5Y-Sf0g4vX-m6g",
                "title": "jacksepticeye"
            },
            {
                "id": "7308e16b3efd48f59e31a05dc0a8fee8",
                "channel_id": "UCS5Oz6CHmeoF7vSad0qqXfw",
                "title": "DanTDM"
            },
            {
                "id": "4bbe3454cd684a41ba289c150ca8d424",
                "channel_id": "UCpGdL9Sn3Q5YWUH2DVUW1Ug",
                "title": "PopularMMOs"
            },
            {
                "id": "80b8942c1d3e4aeeb64aeef2b7c7386b",
                "channel_id": "UCYVinkwSX7szARULgYpvhLw",
                "title": "Ali-A"
            },
            {
                "id": "f6e966c812b54785886e96cfe2606dc4",
                "channel_id": "UCC-RHF_77zQdKcA75hr5oTQ",
                "title": "FGTeeV"
            },
            {
                "id": "11d5936a7dc543d388022c8cadd95ef5",
                "channel_id": "UCq54nlcoX-0pLcN5RhxHyug",
                "title": "SeaNanners Gaming Channel"
            },
            {
                "id": "c784929a35574c0f9ed5378bb6fe1992",
                "channel_id": "UCuj1Ms9_LCsQPSJ4p8nvOVA",
                "title": "Bajan Canadian"
            },
            {
                "id": "2583b73e4980440c8814a7def0f92530",
                "channel_id": "UCJ2ZDzMRgSrxmwphstrm8Ww",
                "title": "Smosh Games"
            },
            {
                "id": "6830186f628b46a48f4fc1ff38bb2c28",
                "channel_id": "UCo_IB5145EVNcf8hw1Kku7w",
                "title": "The Game Theorists"
            },
            {
                "id": "6a5359b960af4b50af79cd5844958a58",
                "channel_id": "UCshoKvlZGZ20rVgazZp5vnQ",
                "title": "CaptainSparklez"
            },
            {
                "id": "8f9f02571c18427cb7f98c807073c232",
                "channel_id": "UCClNRixXlagwAd--5MwJKCw",
                "title": "H2ODelirious"
            }
        ]
    }
]